gigasteam/__init__.py
gigasteam/gigasteam.py
giga_steam-0.0.7.dist-info/METADATA
giga_steam-0.0.7.dist-info/WHEEL
giga_steam-0.0.7.dist-info/top_level.txt
giga_steam-0.0.7.dist-info/RECORD
