Metadata-Version: 2.1
Name: giga-steam
Version: 0.0.7
Summary: A giga Steam API package
Home-page: https://github.com/TSecretT/steam
Author: TSecret
Author-email: timichfull@gmail.com
License: UNKNOWN
Platform: UNKNOWN
Classifier: Programming Language :: Python :: 3
Classifier: License :: OSI Approved :: MIT License
Classifier: Operating System :: OS Independent
Requires-Python: >=3.6
Requires-Dist: requests
Requires-Dist: pybase64
Requires-Dist: bs4
Requires-Dist: rsa
Requires-Dist: lxml
